{
  "id": "statementdog-cmpcl0vtl013001tigzr6c4hp",
  "podcast_slug": "statementdog",
  "podcast_name": "財報狗 Podcast",
  "title": "524.【達人聊產業】突破傳輸瓶頸的背面鑽頭，大量如何用控制器攻克 PCB ft. 簡禎祈總經理",
  "published_at": "2026-05-19T23:02:32+00:00",
  "duration_seconds": 4858,
  "audio_url": "https://sw.soundon.fm/p/HHZK1T/m.cdn.firstory.me/track/clcftm46z000201z45w1c47fi/cmpcl0vtl013001tigzr6c4hp/https%3A%2F%2Fd3mww1g1pfq2pt.cloudfront.net%2FRecord%2Fclcftm46z000201z45w1c47fi%2Fcmpcl0vtl013101ti3u3q9otu.mp3?v=1779192188242",
  "cover_image": "https://image.firstory-cdn.me/Image/clcftm46z000201z45w1c47fi/Psx4xmgA1sfIUuAgmjx83.jpg",
  "show_notes": "<p>本集來賓是高階 PCB 設備商大量科技簡禎祈總經理。他將分享大量科技自創業以來，為何始終堅持自主研發控制器，並透過高度軟硬體整合，提升設備良率與加工精度，逐步打造出難以複製的技術護城河。</p><p>隨著 AI 對運算效能的需求持續提升，高速傳輸也成為 PCB 製程中越來越關鍵的挑戰。大量科技憑藉高精度背鑽技術（D+/-2 mil），協助 PCB 廠商突破訊號傳輸瓶頸，成為 AI 時代高階 PCB 製造不可或缺的設備夥伴。</p><p>▍大量科技＆簡總背景介紹<br />00:41 公司沿革與業務介紹。<br />05:15 公司 PCB、半導體兩大事業部輪廓。<br />56:35 公司應對當前產能供不應求有哪些規劃？</p><p>▍PCB 業務介紹<br />07:47 PCB 產業客戶輪廓＆技術介紹。<br />16:18 背鑽業務在 PCB 產業的優勢＆控制器產業介紹。<br />25:12 成型機業務在光模塊製程中扮演什麼角色。<br />32:25 PCB 產業發展中對設備的成長驅力討論。<br />37:30 鑽針在 PCB 產業扮演的角色。</p><p>▍半導體業務介紹<br />39:09 終端客戶輪廓介紹。<br />43:42 公司的半導體檢測設備優勢為何？</p><p>▍其他討論<br />47:12 AI 可能帶來哪些影響，公司如何透過 AI 賦能。<br />1:04:38 公司如何看本次的 PCB 循環與過往的差異。<br />1:08:10 公司如何看待機器人產業發展。<br />1:14:55 簡總的書籍推薦。<br />1:16:37 投資人可以透過哪些指標研究 PCB 產業與大量科技。<br />＿＿＿＿＿＿＿＿＿＿＿＿＿＿＿＿＿＿＿＿＿＿<br />￣￣￣￣￣￣￣￣￣￣￣￣￣￣￣￣￣￣￣￣￣￣</p><p>▍6/15 漲價，6/14 前訂閱永遠享有優惠價<br />最便宜方案 349 → 599，現在訂閱省 3,000 元／年<br />立即訂閱：<a href=\"https://statementdog.com/pricing\" rel=\"noopener noreferrer nofollow\" target=\"_blank\">https://statementdog.com/pricing</a></p><p>Podcast 業務合作聯絡信箱：<a href=\"mailto:業務合作聯絡信箱：business@statementdog.com\" rel=\"noopener noreferrer nofollow\" target=\"_blank\">business@statementdog.com</a></p>",
  "transcript": "歡迎收聽財報狗Podcast我是主持人維宇在我旁邊的是財報狗頭之總GEN SKY哈囉大家好過去幾年台灣PCB的設備商也受到一些紅色供應鏈的威脅可是自從AI吻世好像就不太一樣了AI Server他要的版從過去的12層跳升到了40到50層板子變厚訊號的傳輸干擾就變多對PCB版的良率還有精度要求就變得更高這也給台灣很多高階的PCB設備廠帶來了很多的機會今天我們就邀請到台灣的高階PCB設備廠大量科技的簡整體總經理簡總來跟我們聊一聊高階PCB設備廠在AI的加成下會有怎麼樣的變化歡迎簡總你好主持人好大家好那大家可能還對大量科技對簡總有點陌生的可以跟我們稍微介紹一下大量科技跟您的背景嗎大量科技是屬於PCB的設備廠主要就是做成型機磚孔機這一塊居多當然我們也有設列半導體這一塊那當然後面還有一些生氣等等的主要的因素還是來自於PCB這一塊而且說磚孔機成型機的部分那這部分我們已經琢磨了20幾年甚至快30年了所以在這邊就是屬於PCB設備的牢場我本身就是我算一算前幾天我滿28年了在大量科技我第一工作是在新竹做自動化只做了10個月這是第二工作因為我在新竹就是在新竹讀大學研究所清大這邊那本身是機械背景的動機械動機械動機械對動機械動機械動機械那邊待了6年那本身就是學機械的然後機械裡面又比較特殊的是學控制器的所以大量跟別人不太一樣就是大量是其他設備廠或者是類似工具機場的所沒有就是它有控制器它是從很小的時候就有了不是長大的時候找別人做的大概這樣子了解我對這種聽起來有點有點奇怪很突兀的東西我都很有興趣所以我想要再插個題我們等一下會聊很多PCB跟半導體不過你剛才講到一個生技為什麼會有生技生技就你們跟生技的關係是什麼喔這個老闆的應援機會所以有人做有人有那種來介紹然後老闆有些興趣就開始找人然後去當然他剛開始所以還在幅畫當中可是也是在大量科技的一個部門嗎它是獨立的公司職公司對OK就是就大量科技底下有個職公司然後去做生技相關的東西了解那剛剛在講的這個PCB跟半導體它也是職公司的方法嗎目前是一個事業部OK然後PCB也是屬於一個事業部就兩大事業部當然我們已經通過就是說今年也會做拆分就是未來半導體會把拆分出去母公司這邊主要就控幾個職公司包含是重要的南京的做PCB的公司那半導體這個其實我們剛剛講說大量科技是PCB的牢場但是之前老闆都認為說不要一直坐在一個行業裡面當然所有設備廠都想沾半導體的邊我們也去沾一下當然也是剛好有機會就是我們老闆他之前是TR的理事長就是電子電路協會的理事長他當了兩屆然後認識很多人然後總人有一些半導體的設備廠他剛好是就是覺得做太累了看你一躍不躍就把他吃下來這樣他很重要一個是Vendor code不好拿的這個就轉過來了就開始做這樣子也是近五六年的事情所以其實這個東西有點像是其實是收購用收購的方法就比較因為我原本在想說就PCB然後要做這個專孔設備到半導體檢測這個有哪些no house相通了嗎可是其實比較像是做整合應該是這樣講你做軟體的大部分很多東西因為它是大腦甚至我剛剛來等一下可能我也會提到說我們玻璃仔板這一塊它是做塗膠那個也是蠻特殊的製程這個部分為什麼你可以做就是你把你的idea想起來接下就是控制它怎麼去做它然後做得好你的no house在哪邊你要用你的大腦去實現它那你也有這個控制器其實是蠻多都可以用的那你與其說大量是PCB的設備或什麼它更接近它是一個軟硬結合的公司就是你前面講的這個控制器我們在設計機器的大腦這件事情但你們自己在區分部門的時候你們是區分PCB跟半導體這是兩個事業體的做法目前是有兩個事業部這樣子那如果我們想要再更仔細的了解這兩個事業部實際他們在客戶或者是他們的應用大概在怎麼樣你可以跟我們稍微介紹一下嗎這兩個事業部的他們應用或者是你們再怎麼樣在區分裡面的產品生那這兩個事業部當然事業部本身是分開的技術可以想通但是算錢總要分開算那負責人我是負責比較多偏向PCB半導體的部分就是我們半導體一個運運長他在處理那這部分的話他那邊就比較偏向於就是半導體的一些光學檢測跟螺網肉這一部分其實台灣的半導體的設備商要切到組織層其實一般都比較難因為組織層都是日本 美國那台灣大概都是做檢測板運或者是動畫這一類的因為比較不會傷到那個晶圓那些當然現在有這麼抓取放那個應該也可以不要伸出來的應該都還好那半導體你只要就是一定要就是台積電日月光西品這些都是我們的客戶都是我們客戶說到這個就是可以賭一點雞所以馬拉雅的居然可以講出來居然可以講出來居然不用逼嗎沒有本來就是客戶本來就是大廠你不做這個你也有什麼可以做對對沒錯因為半導體的加速真的是太少了PCB的話因為我們經營費很久而且我們的成型機的市場率非常高目前可能就是主導的地位目前已經在主導地位比較有規模的廠都有我們的成型機所以我們的生多率非常高那PCB廠商跟半導體廠商不太一樣PCB廠商大陸可能上千家但是大的部分就是那幾家所以他就分布得很廣你可以講出來的PCB的客戶大概我們都會是我們的客戶所以我們再推其他的案子就比較容易推掉因為就像你前面說的其實可能都已經要Bender Code了都已經是合格的供應商了對他認識你的對我們剛剛前面在講所謂的高階PCB可不可以跟我們介紹一下就是PCB所謂的難度或者是所謂的主導地位是在技術的哪個地方或者是做到什麼別人比較難競爭的東西我們講因為有PCB那麼多我們沒辦法全部都懂我們最後我們客戶來講這樣宅板部分我們就設立比較少是我們的客戶目前比較集中在AI的板子AI板子就是高多層對高多層板然後這部分的話跟以往不太一樣他後來又多加一個備專備專其實以前很少人知道什麼叫備專其實我們在法術會所以我就盡量會講這些評審盡量解釋到現在來講大家就有啦備專就是讓他速度快一點大概就是大這樣子大家就知道然後那個Dalence長度越小越好大概都知道了所以我們也在推廣這種科普教育你們法術會最近推廣這個科普放了比較多頁了真的要放肆意其實一個板子要做那麼厚不是那麼好做不然大家都會做像我的客戶的人都會跳槽到某家他突然跳到我們從一家很大的廠跳到另一家做設備最大的廠他就在跟我講這家廠做的高厚度板真的很厲害他們以前碰都不會碰到這種厚度的板最大那一家現在上千了所以這個備專是一個技術然後要有一個一定的厚度然後就是他不可以什麼敲取沒有他其實就是你板子不要太誇張都要做因為你要做到都沒有敲取那是太難了對那如果做得說我壓核都不會變形的話備專大家都會做但就因為他變得太大所以你需要去用其他技術去克服他我剛才還沒講完就是他的難做的話有幾個那個高厚度板有幾個第一個就是我們講的把它一片一片因為多層板是一片一片壓起來的壓的這個技術其實很難那這個部分設備大部分都是德國的是德國的一家德國那一家第二個是專孔一專的生孔專也不好做生孔專這個是平技術因為大家的一般的專機專孔機不會差太多差一點點不會差太多生孔專是看專真看專的技術第二個生孔第三個就是生孔電鍍你要鍍得這麼好很多人都死在這邊那個電鍍孔沒有鍍得很好裂掉你沒有檢測就是賠那我的客戶之前兩三年前跟我說他們那個賠的就是幾台兵力就賠走了因為那個tripper不便宜上上去就完了最後一個就是備專因為備專就是我們講說專到剛剛好剛好那個點不能讓它破又不能流太長那就是難難在這邊那目前這幾個都難點但是備專這個尤其是難中之難就是要做得好其實不簡單因為很怕壞掉但是備專因為備專衍生出來的又有這些東西檢測這些很多的那檢測部分就不是我們做那是可能是日本Sray那期在做檢測的了解那個電鍍不是什麼賣充電鍍是類的那是電鍍對那是一個剛剛是說那個電筒那個這個還有壓的那個是壓的那個其實很難那顆英文不是那那部分的所以我知道他們都買的就是德國的伯克就是那一家那家也是排隊排得好久這樣因為現在有混壓就壓了壓去了剛剛你們想到的各種反子壓了壓去了所以這個點就是在我要做專在做電鍍的時候就算這麼厚的板子它一定會有些變形可是我還是能夠做到這個就是拿的地方對當然你壓就是要壓得好所以但是你壓得好不好其實就能看變形裡面有沒有它的有沒有變化量沒有很大你其實看不出來就是要測了才就真的用了以後才知道對最後專下去一分兩定對專完才知道那我就在就說要誰就你就死有一樣底下也沒有油你專才知道對每次都在抽下去一億噴了裡面什麼都沒有那像有沒有提到說你們是主導或者是你們這幾年在做這個科普代表你們一定更早以前就開始在研究這個技術了這個技術其實蠻久了那我們跟我們科普其實老實說我們有我們稱型機有專統機稱型機的這類型的機器是比較早一年出來因為大家想說稱型機要早點做就可能找大量才有那種做可以做奇奇怪怪的功能出來是那這部分就是我們一家科普最近也是蠻紅的做那個低軌的最大低軌衛星最大那一家那之後我們做那個氣劑成型機做好之後呢後來也是機會這家目前做備專產他是找我們這個大概10年前的事了十幾年前的事了他剛開始就去機器做然後那個底下工作人員說德國機器還是比較好問題很多剛開始去問題真的很多因為剛開始的時候就有一個好處就是科普可以容忍因為他的單量沒那麼大他可以容忍因為他是開發他已經決心不要跟德國那家做了因為德安叫他來優秀就很窄不想讓他做那就是全心培養我們老實說那是很感謝他們因為他們蠻有經驗的那經過這幾年摩河大概就是穩定了你說之前什麼甚至我們的問題發生問題的查找能力都還比德國的還要好就是有固定合作的對象要有練兵的機會對 要有練兵的機會所以你是客戶跟我們客戶給你們機會練兵然後大家就不斷的改進其實就跟台積電拉台了一大堆台灣的供應鏈是一樣的概念就是扶植在地的供應鏈大概是聯合客戶也不是省油燈他那時候是培養你家也是有策略的就是要找一個神坑獸是殺爆第一對 要找神坑獸是什麼現在因為大家出來這種機會就比較低了那為什麼德國那麼厲害他們做得更長他們做個開個品牌效應老實說德國做的機械的精度我說機械精度老實說沒話講他那個光他們的老師傅在堅持那個磨那個花崗岩磨那個是什麼為了那個一兩個mew在那邊一直磨磨的一兩天好 但是做精度真的是沒話講那這是客服拽了一點這樣沒有價格也沒話講對 價格真的也沒話講老實說但是他們的軟體老實說沒有我們的好用然後深入客戶的據說你一個地方可能拿100分可是其他地方尤其在服務室幾乎拿零分那也沒什麼用對啊 中和分數就很低中和分數就不是那麼好那我們這個就是我們就號稱高CP就是價格我可以比大陸的高一點點但是我性能可以比照德國甚至我可以超越他的好處就是他的一些品牌效應很大歐美當時也會指定說我就叫德國你用德國可以做我才下單給你那是甚至只要說這句話沒者對啊沒者 對經過這幾年的改善我們客戶也是很堅持說要挺我們這樣子一起說服所以目前這種狀況已經很少很少了了解那如果說笑練兵的機會其實就想到說可中國就是這樣子嗎他們如果想要扶持什麼產業我就全部一起練兵會擔心這個嗎對 沒錯他們也蠻積極在這塊尤其背鑽這塊很積極在攻那其實他們有很大的他們的關係可以做得很好但是他們就是少了一樣沒有控制器他們的控制器都是買的許茂他們有自己的大量有自己的其他家在背鑽這塊是沒有自己的沒有自己的話就只能仰賴別人別人也要賺但是最大問題是說當客戶有問題的時候要經過你去轉一手那其實已經失真了像我本身在對客戶如果客戶很急他說可不可以明天要那時候可能是10點能弄到11點 12點就給他因為他們真的很急說機器已經停在那邊了完了就怎麼辦那隔天不會被罵死嗎機器已經停了可以趕快把我處理一下印鈔機嗎哇這其實也是真的蠻硬的真的覺得硬可是真的就是印鈔機對我的超標快要硬不出來快一點那這個控制器你要說為什麼中國廠商他們他們那邊他們不自己做控制器這個人的難度是什麼大家都想做不是說不想做是他們也曾經都做過包含台灣的競爭友商他也經過前兩年好好宣布之前有幾家都比大量大做成型做專管都比大量大但是他們有幾個策略可能我認為是沒有好好走做控制器當然這一塊他們也想去突破但是自己沒有人也是圍外就圍外幾個控制器想上去做但是碰運廠商他做的是販用的不是專用的所以我說如果控制器它能讓馬達動只能做1%而已還有99%你是沒有做的你要很貼切的去知道客戶要哪些功能哪些是客戶沒想到你幫他想的這些要做的完整才算完整當然只會做控制器那就只是個商品而已他沒辦法去貼合客戶的東西他們想做所以其實還是有很多接近服務業的 know how你要很了解客戶的取決對因為這個是看不到你可以我也可以我去找人做但是通常失敗已經有兩三家甚至大陸的晶升對手他們也是錢非常多他們可以找很多人來做但是也沒有做出來我懂了因為他們應該是沒有那個vertical knowledge至少有一個頭至少有一個頭在那個頭都沒有他怎麼做旁邊的人是說你這設備你就會動就好了還有一些妹妹跟爸爸對大家就是要你業內的人去才會知道沒錯好如果我們來看大量的財報在2023、2022實在就是為福獲利可是到2025EPS突然跳到8元就是這個中間是發生了什麼事情有沒有什麼故事這個應該是之前努力突然就往商跳了這剛好是實際隊老實說不只我們其他很多的設備商然後我們的客戶也是藉著這一波大幅成長大量的幅度算是比較大的因為我們這一塊本來就市場是PCB的成型專孔的以往最早以前沒有類似之前它是算PCB的資本支出最大的就專孔這一塊那是一般的專孔你比較就是被專或者CED成型這一塊它之前的量是很少的大概一年大概四五十台當你高頻高速在成長的時候它的需求是翻倍在成長像我華州家講說去年的量是多少我今年第一季就全部都接完了這是法術會講的所以這講應該沒有關係對法術會講的這個是不是說我們多厲害這是市場需求市場的需求在封口上然後你剛好又贏人家一點點這部分其實老說德國的機器也是滿單但是他們產量太少為什麼他們會開不出來你們有辦法供應出這麼大量可能德國那邊的你要加班可能不行我們在大陸比較沒有人心一點這裡有錢趕快來賺大家都好其實大陸都是供不應求只是我們能夠開產能開得比較快一點我覺得會做人其實不多中國一家德國一家大陸有兩家大陸兩家然後中國大陸一家然後德國一家總共就四家嘛這樣子對啊沒了然後板廠的需求很可怕我舉個才有例子就我們板廠他剛剛說我們今年會買假設他去年十年買了100台設備他今年就直接說我今年就要買100台甚至更多對結果我看我就傻了一年買超過十年的量這樣子中國人真是有空很因為他是平景至成之一是了解這個目前有沒有看到說他們全部都是在我們剛剛講的AI版的這一塊嗎還是它其實是有不同的需求備專這個大概就是高速的AI是算高速的那天上飛的有沒有可能聽說有可能天上跑的有可能是就是這個有可能但是還快比AI這一塊那個專孔的備專部分還有一個就是傳輸的部分最近就是光模塊也是非常的我在法師會講說占的比例大概就是10%半導體90%PCV90%PCV大概有兩三層是高階的那高階部分有大概9層是備專然後一層是CCD的成型那現在可能CCD成型也往上跑因為他這個是光模塊光模塊在用的對光模塊的成長也是非常快因為以前成型機就撈個那個主機板方方快快的不曉得有沒有看過那個大大的補給板有有有那個在三分鐘做完先塊一塊板子做可能要六個小時 幾個小時所以它的需求量就一直在上來喔我以為對於這個以中端成品來說我以為在AI版它的量應該還是遠大於光模塊的量的就是市場的需求板子因為AI版的比較多家對光模塊比較少家所以比較集中所以就算兩邊都在成長可是光模塊這邊的這個佔比居然還可以再拉高對因為它最近的量也蠻大的真的但是就是因為之前佔的比較少對啊之前可能就是只做了一些一些當然現在就是一次買是兩位數三位數在喊的所以那個量就突然就變大了那背端這塊其實也有在喊但是就是持續這樣子而已是因為光模塊已經被訂完明年的對那我會不會是很清楚但是就在吹氣氣了對因為產能已經被訂完了所以只好買機器了沒有真的因為剛好我前陣子都有去找包含剛剛也是因為它四代在疊帶是不同的像之前是400G現在目前800G未來是1.6T是越來越難做然後越做越慢然後越吸載越需要越多是你們這個時間應該是跟它的速度成正比它越速度越快你做越久它的精度它要求的精度之前它有一個外套棒的邊到我們切的邊是一要求是100M那400G的時候800G的時候就變成50M的最大的值1.6T就要求25M就幾乎是成極速在縮減那個精度就是你要考驗你的你的穩定性考驗你的做法這樣子是你點而且它業界導入的速度就突然之間變超快本來還想說800G這個量到底什麼時候才開始放量才要開始變主導瞬間大家開始在討論1.6T了大致就跟你說我要跳過800G現在800G還是主流對啊你之前也要跳過800400要800了他那時候覺得好像把我的G不會起來對啊你覺得好像不太對為什麼很失望其實這種東西做這個板子對還是隆段在自己家手上是做板子的做板子是我們這邊是這個成形機你剛剛講的這個成形機對這個成形機它在製程裡面是什麼樣的角色就這個光模塊他們這個機器它扮演的它做的事情是什麼它就是把我們在做板子是一大塊然後把它切下來以前家把它切下來就好沒有什麼工資就是切著可以裝就好了它現在不是它現在要切之前有那個像你顯示卡或什麼卡都有一個金手指金手要切就切到金手指的形狀那現在那個像之前的蘋果的那個插頭它旁邊就要做跟那個對齊然後那個插那個金手指要跟邊要對齊所以要去切一粒照去切齊那光模塊就類似這種的那光模塊跟那個稍微比那個插頭USB大一點點可能也差不多但是它要求地方進入要非常好才能走高頻不然它那邊也是有危險就是我打下去留太多也是有危險那我們專注在這裡那裡面的設計我們就不曉得了解因為它有那個你要對你那個移掉就那個叫什麼copyline有點像copyline的那種東西我不知道大家知道什麼是金手指大家有錢玩過卡帶有沒有小時候打那個電動不是拿那個電腦板在上面一個一個的銅的那個接點就是金手指就大概是那個東西所以現在應該進度要超高因為它那個越來越小然後那個它越放越多顆這算越多顆怎麼應該這樣講是對越精密越精密所以那個棒的應該要更細就對了這個成型機跟剛剛在講的備轉可能就是目前成長最快的兩種原諒我理解你成型機是只有那個切板子而已嗎我們對我們成型機有切板子那切板子不同形態那一般的切板子就是一般成型機那需要去對位的就是CED的成型機那我剛剛講光模塊這邊屬於CCD的成型機那我們就把這個區分成就是一般的切型那高階的就是帶CCD的是對它就是重點就是對位對這件事聽人家CPU在對位差不多意思像我們看到其實在光這邊他們疊帶升級的速度也蠻快的這個設備也會需要這麼頻繁的去跟美一代嗎就還是我們就是改軟體還是硬體就是會就必須要改對於專孔跟成型這一塊其實它的翻用性還是比較高的那如果是切型那最簡單我們只要你進度可以保持二十幾年也是有人在用所以就是為什麼大量的成型機在市場上那麼有名而且在二手市場是非常講述的因為二十幾年的機器還是可以用得好好的這個還有二手市場的報價是不是安傑卡拜談哈哈哈哈東西都太好對 換不掉不過它的量也是持續在成長是那專孔其實專孔只要轉速夠其實二十萬轉的這個世代已經走了十幾年了應該也沒什麼多大的變化這個變化就是一些小東西譬如說做自動化這些有的沒的附屬的那備專制後來出來但是備專用的轉速反而比較低因為它的孔比較大嗯那就我一說即使下一代出來之後你要去取代專孔除非這個製程不見但是你專孔有個新的變化除非是說完全不一樣的東西但最近有人在講是立走要振動去專的部分那這個是另外一回事但是一般的這個桌子差不多了正動作專是一直撞的那種對不對嗯就是有的拿一個像錐子一樣不是也是磚但是那個磚的部分會振動喔理解為什麼這樣好處是什麼嗯它退血比較乾淨然後它把那個裡面的那個甩出來啊退血它一般磚的時候會殘血對它殘血會造成你孔的不良或者是你的刀劑說明會磨損那你正動作專的就是它的血會比較容易排掉喔太神奇了大盾什麼都想得到怎麼想得到專業的領域有專程去想現在有的工程機可能叫多改了振動的功能這個可以嗎我們其實原本有但是真的比較慢必須要用原件它去振動會比較或者是喔 理解因為這感覺要再有一個垂直的就都要垂直的馬達之類的有不同的做法當然我們也有在研究這樣喔 了解了解其實專孔是很多現在大家突然懂專孔大家突然對專孔很有興趣大家以為就轉頭轉一轉馬達把雷射轉一轉你剛才講那個磚你知道最近那個水域上面有五色鳥很紅嗎我不知道大家看到那個就那個信義區信義威秀旁邊就有個樹它沒有個五色鳥它就把一個樹就磚了一個洞在那裡就很有趣了就想到那個在那裡磚這個東西對 專孔這個就是困難的不過大量應該是這個監總這邊應該是基磚因為那個ABS用雷磚對 雷磚其實台灣沒有人在做但是目前最大的還是在日本那一家是聽說不好買雷射頭不好買他們是自己做的雷射頭本身就是一個那這兩個的比較是什麼就是我們用的機械的物理磚跟雷射磚它的比較優缺點是什麼雷磚的話它是做盲孔盲孔就是表面它因為它磚的不深它就是底下一層同配的然後上面一層童博家那個機材然後把童博打穿到底下一層然後這層在電路所以它就是做盲孔保保的盲孔盲孔盲 盲 盲看不到那個盲孔看不到盲孔對 看不到對面的沒有直接戳戳爆沒有抽到現在抽到底了對那它就是孔可以做得很小而且它的速度很快它是算秒是秒幾百孔的甚至未來有沒有數據更新我不知道就知道秒是幾百孔以前然後飛秒雷射對啊 我剛想就是這個東西英文是一樣的它有很大的能量去把它燒掉對靠燒的那機械磚孔不一樣機械磚孔是打通孔或打比較深的孔它雖然有可能是蠻孔但是比較深的孔空間也比較大如果打譬如說0.2 0.30.3孔叫雷射慢篇去打那就打好久才打錯砸到穿當然也有人是會像那個NL的是一成一成打一成打也有可能也會但是它的成本就高了很多就雷射要得的能量可能也比較高雷射那個我就比較沒有意見了解我在想這樣子就剛剛Skyle說你們讓錢很難賺就是你們用太久打機器用太久了這會是一個缺點嗎你覺得或者你們要怎麼樣說因為等於說我如果廠商我沒有要因為換機槽也很久我其實也不太需要換機我一台可以用20幾年其實我們之前都有想法是說在20幾年前我們說成型機這個月生也很好可以賣舞台怎麼那麼多每個月都可以這樣買為什麼他們一直買然後一兩年為什麼每個月都可以做10台為什麼每個月做20台為什麼他們的整個的心態一直在變以專孔計算來講以前的專孔大概一個板子裡面幾個孔而且孔都很大反正0.5的孔最早期0.5很大孔現在0.3 0.2然後孔就很密以前可能一個板子1萬孔後來變20萬孔才變成10幾萬孔變成幾十萬孔所以孔數就越來越多一樣的板子對1萬個板子所以它需要的量就一直在翻倍然後還有就是而且你小的孔專不快越小的孔專得越慢然後你的材質越來越硬以前就早期有一段時間一般的FRO板一般的板子後來變無魯樹板還TG板都越來越硬越來越硬的時候你專的越來越慢你的刀子壽命就越來越短現在又要講M7 M8 M9對Q classE class所以現在還在炒鑽針為什麼鑽針就是那個到M9的時候它的壽命可能就300孔或者300孔以下以前可以用2000孔那是不是我生意就變了5 6倍所以其實就隨著我的這個精細度變高我這邊的孔越來越小可是我要專的孔數可能越來越多這時候就越來越多的設備對設備需求就越來越多幾個月越來越難做總不會有越來越好做這個設備多大台很大很長因為我在想你一個板子要穿幾十萬個孔可是設備這麼大台沒有它那板子大概板子就是0.5米的寬度然後大概是0.6 0.7的長度然後整台機器大概是4米多然後再2米多這樣子也沒有算很大算中型4米多的機器算中型有 上次長得很大上次在網路上有哪個展覽對 我們看算很大但是其他的機器也更大的對雖然但是你擺下去很狀況整個磚孔房幾百台就在那邊哇他們那個都很狀況然後哇一台就不都是磚孔機對 我想那幾百台磚孔機板那邊光走板廠吧就很大因為板廠產生算那個極尺就是幾個平方米平方尺平方尺都要對所以你去看它都是幾百萬平方米它可以做這個東西做幾百萬平方米你就看你就你看那個散了我看不到後面然後靠沒那麼誇張這很大就對了對啊真的是喔因為那個我覺得這個其實很有趣因為這個有好幾個Psycho結果剛入行的時候是那個財務顧問那一陣子是那個大家第一代板廠不行的時候所以很多人賣板廠對啊他就賣那種他都是大概三四層板吧或者是什麼八層板之類的然後他們在賣那個賣那個你就看它那個線因為它以前的那個就要怎麼講就是它那個機器又更大台又更長所以每一個人都是所以你是帶起你的潛在買家去看是不是沒有 你去撥客就是財務顧問就是撥客嘛對他賣我也要去看他我賣的人也要去看嘛對反正我們就無聊也去看反正我是撮合他們嘛你愛不會這不錯就類似這樣子我那時候去看就覺得超壯觀的就台灣那時候因為台灣早期有很多那種台灣的都沒那麼大你去看中國就一兩百萬尺我想說我考台灣是比較小的對它台灣有那種小小的工廠然後是那個好幾間民房接待一起的跟你去中國看我考每個都超級長就是那個這塊地可能全部都是做PGB我就覺得那個所以我們可以這樣講嗎就當我今天如果要的精細度越高或是我專的孔越小其實我一定就會需要更多設備原則上是這樣而且也會發現奇怪為什麼那個PCB買不完那麼多買家一直在成長搞不清楚因為大家玩AI對 因為其實真的會想就是說可是就那幾家然後一台可以用20幾年為什麼可以賣這麼多就是每一年越賣越多是為什麼所以說那個備賺這塊是之前是等於沒有人買所以它這塊都要新天購新買的就要新買像剛剛有寫到說那它的這個我越精細我的鑽針的使用狀況其實越少對大概是這樣鑽針是有給你們買嗎不是 精細越硬因為未來的那個板子都越來越硬還要越小越來越小 要空因為我會想像到你越小的空你的那個鑽針可能要越小沒有 那個玻璃會越來越硬我剛剛講那個格拉斯鑽波鮮布的那個東西會越來越硬之前大家在講那個Q格拉斯超級硬對 都是硬打包都有關係鑽針我們沒有做鑽針就是定義家公司OK你們會有搭配的嗎還是沒有隨便他們換就是朋友友好廠商應該說我可以去選各家的鑽針嗎對沒有那個是板廠自己決定的板廠自己決定我要用哪一家的鑽針那都是標準的規格是標準的要抓的地方都是標準的了解就是一個標準品的概念是喔了解你也可以買日本的會嗎大家都買大家會買日本的日本也有不會日本也都滿滿單的這個鑽針你知道它的不同家的差異是什麼嗎我這個老實說只聽到說這家比較好那家比較不好有些看他們用的習慣當他們說好跟不好的差別是意思是什麼是壽命嗎還是良率良通常是僅良率會不會把東西撞壞掉喔就雖然我達到規格可是有一些就是你雖然表面上達到規格但你還是良率比較差對因為總有那種把孔村壞掉或者是哪邊塞孔那些有的不良的狀況的產生為什麼這個就要看他們鑽針的設計不曉得了解好剛剛聊了蠻多在就是PCB的部分再來我們來聊一下半導體這塊就是你剛剛有跟我們大概介紹了一下PCB這邊的組成就是先進的大概2 30%然後倍賺90然後10%的成型那如果用這樣子的架構我們來討論半導體這塊的話半導體這邊大概是怎麼分的呢半導體幾乎都是先進沒有說那個沒有說一般的因為他們目前都是交先進製程就是光學檢測跟那個弱昂肉的部分就是自動化部分那這兩塊的比重大概怎麼樣也不一定他們這個不一定要有時候因為目前的量沒有說很大就是有時候這樣光學檢測的那就特別的貴特別貴來個一台就賺很多哦目前在這邊的規劃大概長怎麼樣看到什麼樣的情況是這個可能是未來的一個機會嗯目前還是跟著大長走對大長走那他們到哪邊就他們指哪我們就打哪對他們下指哪他有些是還沒開出來產能但我們希望這個產能開出來之後我們的這部分的一些訂單會也跟著上來嗯他主要是這樣子是有專注在哪一塊嗎比方說像面板疾風裝或者是我們剛有提到這個玻璃機板這個目前比較看到的走道都是玻璃機板這一塊我們半導體是沒有這一塊是屬於PCB這一塊的哦PCB這一塊玻璃機板因為我們去年就教了intel教了兩套設備去那邊就是做專門做玻璃機板的一個最後製程的東西就因為它這個跟跟我們做AI眼鏡圖交式相關的所以是貴在一起半導體這邊的話當然他們也有做玻璃的那個什麼FANFAN RPLP不是FAN RPLP就是PLP類似這種的東西都檢查我覺得他們家是應該是AI比較多就是AI那種MachinesMachines比較多Machines比較多對講到一點就AI就是那個Inspection高級點就是兩側對他們是說兩側我好奇那個如果我是專玻璃的跟剛剛我們前面講的被專玻璃跟被專起來他們沒有專玻璃專玻璃就用雷射用雷射專吧對用雷射最部分我們沒有我們沒有了解所以在這邊比較多的就是在做封裝的檢測這一塊是嗎對然後這邊的技術已經定了嗎大家還是還沒有因為我算一次我記得去年問的時候他們說其實幾大沒有定對所以他們就是還在配的電光因為這個去就在那邊一直demo一直改一直改這樣子當然就是希望他早點訂早點量產現在早點拿錢來早點放量早點放量花工的錢都不收苦澡長得脫對啊錢勒但這塊對你們來說你們遇到的困難點是什麼是要一直改嗎還是有哪裡有技術上的困難技術上應該是還好但是就是客戶會一直開新的規格對所以主要是客戶那邊他們還在想辦法把它兜起來就對了對他可能要一級多要不要實驗機要多什麼功能出來這樣子目前也還是在一個頻繁疊帶的過程中對就是在往上突破但是就有點障礙這樣當然不在你們的隊了障礙在別的地方障礙在別的地方不知道是誰不知道是誰弄的因為聽起來就最近突然很熱我們剛剛在外面也在聊最近很熱就是因為那個業人愛B的關係對啊對啊因為反正未來中間會放玻璃的有可能大家好像在大家在期待吧大家都我覺得現在就是大家一直在看新的技術只要錢在那邊大家就受不了了所以各種新的技術就受不了了看到黑影就先開槍了大概是這種感覺了解在這邊檢測的我有好奇跟其他可能就以你們在做的設備來說你們的優勢或特點是什麼跟其他的比起來這邊也是客製化比較對客戶的服務會比較做到然後自己也有能力去做這些因為我們的這邊的軟體的部分還是比較所以還是控制器最快比較可以聽起來控制器好像真的會是一個蠻大的優勢對不對它這邊比較因為它屬於製程上的東西跟狀況成型不一樣狀況成型它是比較偏向於工具機類的它這邊比較偏向於自動化檢測類的所以這邊的兩個領域是有點不太一樣那會是不同的就是各有各自的事業部自己去做自己的控制器它那種就不叫做CNC控制器那只是說一個系統這樣子但是他們主要和在光學那邊要他們處理比較比較深入去處理這樣子光學的部分聽懂了請教一下你們那個控制器你們是有搭固定的廠商去那些譬如說那些馬達羅感那些的這些都是要配合的可以自己選可以自己選反正規格內都OK就對了可以要當然會試試到好我說規格是試到你們OK你們一定有固定配合的對像馬達那些也都是要因為有一些馬達廠商會寫那個他們會寫他們自己的控制的軟體這部分我們不會用對我們就是當他他只要動的照我的方式給他動就好了是所以每個應該就是這個對不對簡單的就是Rodicot的No號對了解因為現在應該有說廠商就是馬達然後就是一整套給你就一個模組這邊帶一個那個我是說工具機的那如果直接是廠商直接自己開發的這個就比較少一點對理解就是控制器的廠商他會一整套的去賣公版賣給你對 整套的去賣但那樣子可能就客戶會好操作嗎就缺了點東西沒有 他是做販用的東西沒問題對比如說他只是把東西切得方方塊塊的或者是車床洗床那種標準東西他也可能會添加一些特殊功能但是大同小異這個是對他們是沒問題的但是如果要切到比較精度比較高的扣子比較專用的他們就不能說他精度不高說他們不是專用的市場因為控制器他有分兩個市場應該就是也是販用的市場那販用市場就是工具機我們台灣其實滿多工具機的台灣的工具機的廠商很少有人自己有控制機也就都沒有都仰賴方拉克必須洗洗免止或者是其他歐洲的一些控制器都是外購的多那這些都是屬於標準的反正他的馬很多都跟方拉克是一樣的方拉克是一樣的那一種的就是專用的這專用的話就是屬於偏向像中央機身影機這是屬於專用的他長得非常像又是一樣的東西但是他的那些功能就是完全是完全裡面就不一樣要參雜的東西不一樣當然我們的有一個日本的經商他也是用蘿菇蘿菇就用那個方拉克的控制器去做PCB但是它的最後是沒得買為什麼就Nohaw差了點嗎不好用有沒有可能未來AI可以讓它變得好用而且它很貴也很貴日本人比較貴還不貴因為我在想說如果今天我只是在有沒有足夠的DomainNohaw這件事情所以讓它的軟體去調校的可能比較好如果關鍵在這邊的話有沒有可能AI能夠去調整這個泛用的程式嗎讓它變得可以那你要有它的程式你要它開給你所以它可以開在AI底下你就有一個大的你要注意的就是你的自己的背景知識或專業知識要夠強對但你要告訴它怎麼做它才會幫你做你隨便告訴它做它就隨便做給你真的對這個的話因為我們最近公司也在導AI我自己也在用這樣來寫了就是那個程式太多太多但是你把它掛上去它去分析之後它會照你的股價照你的方式去寫出你要的東西給你那這件事情其實對我來講我覺得我就跟我們的研發協議講說未來我可以推測出來寫空置器門檻會降低對因為我只要有一個股價所以我們股價在保護得相當好萬一流出去人家說你照這個幫我寫link出來對啊就死了對啊所以它模仿能力非常強它模仿的比你還厲害嗯對啊這個就是我覺得有可能的東西就比方說像你投資你有很多的專業知識這東西其實都如果它都有機會變成一個SKILL就是靠扣我們的那個SKILL其實是有機會就直接就是用你的DOMINON號去做到這件事情好像是有點機會的是有機會的是不是有機會是事實上現在大家都已經在我們已經就要這樣做了就是我會把我的目前的東西全部DOMINON成SKILL對然後未來我就是用一個東西就是說你幫用這個SKILL產生另一個東西對它就馬上產生出來了對啊哦所以資安很重要這個我說我真的發文有搞不好對不對欸我買號型那你們用的模型是你可以照羽毛還是你們的CALCO是比較允許程式聰明一點可是像有些人就會說你用CALCO你的程式嘛就被CALCO的看光光你的東西就被CALCO看光光它不會在意我們這小公司吧因為我們是偶像公司不要擔心太多OK真的欸沒關係這樣子好可怕對啊因為我覺得這是一個你可以想像說如果你這樣做你一定感覺到的明確的好處嗎如果有公司就說啊我們擔心資安我們要用這種小模型它就是做不到這個程度這個對競爭力會有影響嗎你說有用AR沒用AR對啊當然有影響就是說我自己我就很困擾是很多東西我要自己做對那當然有人會入市上來那將那個過程學習過程非常的慢對啊我們訓練一個訓練出來最好最好大概要一年多一般的可能要兩三年有些人根本就訓練不起來那你有這套之後它會變成說你會把它分級一個就是使用SKIR產生你的東西的一種是你如何產生SKIR的嗯這個部分的話就是交給比較高手去做外面那個就會交給一般的那去做它一樣可以做出東西做出你要的東西出來但是一個是在發展未來一個是目前的對未來是個降重你如果沒有使用這個的話你就還是照老方式一個月看不小心可以做這個一堆bug就跑出來對但這個其實對我們自己算一個軟硬結合的號稱軟硬結合公司還有LID軟體在裡面對於軟體的部分它其實是蠻重要的蠻重要的是你不要說寫個bug留在外面我要死了那個不小心引爆就很麻煩對啊我覺得你們如果現在已經在就是說你們公司現在就已經在用SKIR而且有你剛剛那個說法有比較資深的老手他在寫SKIR然後比較新的人他就是在用SKIR已經有這樣子的一個流程的話而且你們走很快因為我們本身就是軟體但是SKIR也不是自己寫也不是自己寫就這樣叫它照我的結構產生SKIR就好了對說實在應該是大家會覺得當然是設備上就是硬體公司但是依照你們之間軟體的這個軟體加硬體軟體加硬體的所謂是多的有很多軟體公司到現在還不會做到這件事情可能有個人的可是要到公司層級有很多公司有很多軟體公司都還沒有這個我覺得就是大家有沒有接受到新的知識這個東西就真的是真的是很好用好不好不要說我一直抽這個你當時在我可以想像說個人使用很好用我有一點好奇的背後的故事你說嵌入到公司的對 你要進到公司的這個流程然後說我們以後要開始這樣做這個是怎麼起來的其實最快就是寫軟體老實說 軟體就是對他來講就是寫扣的是AI目前當初最大的對那當然其他的領導比如說產生影片產生聲音那是其他的事情那我們今年開始我就有規定他們就不管你各部門有沒有用到寫成事你們就去想辦法用AI做出裡面的東西你要產生影片或者產生東西你至少要去接觸它那我們在每個月的時候大家也都拿一些成果出來報告那這時候我們就慢慢去達見他說你應該要把這個東西應用在你的工作上面或者是我什麼想法你幹嘛能不能做得到就慢慢導到AI那目前AI的企業化其實我們已經開始再弄了但是最明顯就是寫扣它是最明顯那其他的比如說我就跟我們昨天就跟我們那個財務講說很簡單你就把你東西弄弄起來就叫AI說月底到產生報表他就應該產生給我們他應該完整整整把產生給我而且經過檢查而且是沒有問題的你要去微調你再去你再去看一下就不用費那麼多工了這樣人的價值就會變大變高我覺得目前就是有去請他們去用這一塊因為其實蠻多我們是覺得不夠好用不是絕對不能用對對就有點像是說我覺得這個是Cloud Code的一個非常或者說我們到Codex也是就進到本機有一個很大的變化就是以前我們在用Web版的AI你可能你會叫它調整下次它還是會有一樣的問題它就是選不太起來就是沒有那個Skill它沒有那個Memory它就是選不太起來可是當我們開始用到本機就是用Terminal用Cloud Codex的時候其實它的那個Skill它的確是能夠一次一次的更接近你要的你跟它說這樣子不對你要記下來它下次真的就是不會再犯這樣的錯誤就基本上不會如果你真的要非常Cloud Code的話要先讀一下記憶對啊你就再叫它寫個程式去做直接Rubes的檢查其實也可以對啊就真的我是覺得蠻可怕的就是對於未來這個公司的形態會變怎麼樣然後你會覺得我的感覺是可怕不是你啊初階工程時射射發抖什麼都沒幹掉工程式還是要經過那個階段對你有沒有經過那階段你後面你的公司的價值上來邊就是你的LOH你的LOH跟你的一些data所以你要data要留住不能外露然後你的LOH要知道這個才是有些LOH才是你的公司的價值可是像這樣子培訓的方向是不是會調整一些東西就有可能某些東西變得比較不重要某些東西變得很重要我其實是在做我們公司的東西的時候我其實也會有這樣子的想法就是其實這個流程變得那麼多未來到底要比較注重在什麼東西然後哪些東西會變得相對來說不那麼重要可是又好像不是那麼清楚目前都是在摸索大家也是在摸索因為我們不像美國那種人家用得那麼順手那因為你一個人是最好用因為就是那個人做像我就是寫成是就是對我來講最好用就是自己做那寫成是做什麼但你一群人在用又完全不一樣所以目前對我們講都還是在摸索中但是我們方向就是未來就是要導入就是企業的AI是了解了解真的覺得非常的有趣像這個變動對走的真的是前面真的是前面真的是前面對啊就是現在你能夠讓全公司有剛剛那樣的流程其實我覺得真的是不容易要忍耐對而且上頭一定要很積極推動這件事情這一定是風行草眼對甚至要有某些的像剛剛可能說我們每個月要有這個要KPI對然後這個團隊就說好要這樣做然後我們就要改然後就要這樣做這一定是要有上面的人有某種的指示不然大家其實懶得動因為原本的做法習慣了嘛而且原本的做法沒出事我用新做法我還要學對不對然後有可能我們會做錯對啊是叫做沒錯好那其實在公司在法師會上面又強調說現在的訂單非常多嘛對我們剛剛講的四家產能都是滿載這樣子你們在接下來有什麼樣的規劃去做這個公布應求的解決其實我們一直在做就是外國被罵死了也就是說訂單10月11月那有這種事那就是就是目前以目前來排就是這樣子然後我們也想辦法積極去增一些產能出來那增產能不是做做做做但是我們就好出什麼我們的產能是人嗯為什麼因為我們是組裝機器那外面的是大概我們就是發出去請協力商賣進來那這個量目前為止還滿充足的就是有幾家供應商幾家那沒有也有瓶頸部分他們已經自行想辦法再提升了所以你們的料是沒問題的是組裝的人比較缺那組裝的人場地跟人現在他們也是很怕說那個人情到時候不好那我這些人怎麼辦對啊對嘛因為之前就有發生這種事就是突然可能要是突然訂單就往下然後人也老闆可能這些人在做什麼沒事做所以就會有一些問題出來那這部分的話我們目前就會自己當然人還是要進但是有一些部分就是會像台灣的工具機都會有些是外發外包外包是進來我們廠內然後請他做甚至我們會培植我們的友商就是不是進商是友商他們沒有做這一塊的但是他有場地友人我就把一些之前比較基本的東西把他發出去然後培植他們把它做出來然後做出來之後就多了一些產能出來因為傳統工具機那邊現在市場不太好嗎有先制產要看啦又開始哪一種工具機看不一定但是這種人都有這群人就是外包這群人那我講那個他們自己本身也不是做工具機在一塊的就是我們培養他們然後去把整個東西建築他也是蠻有興趣的OK就有去扣過一些外包的策略採購的策略的調整模組化的生產這邊會有譬如說機民資料一些Domino Hub的外流的疑慮然後再來就是像這種組裝的人他們培訓起來算容易嗎組裝的是要點時間但是我們這個還不像工具機什麼產化師傅要幾十年的這個倒還好那照手法去組快跟慢而已就是有些人一個小時做一個人就可以拖一天但是也可以慢慢學可以學得很好應該也不會有多大的問題那我覺得既然就是不然你也做不出來你讓我知道有怎樣你最大的機密就是你的控制器他還拿不走就是反正他還拿不走機要的人不要因為他你都切這麼細他應該不會知道他只是組裝他還不走那你說看機器外很設計那我到其他客戶去看我也看得到所以就像你剛剛講的可能最主要的還是在控制器的這塊這塊是我們弄好這顆就拿不走了還有我們會申請一些專利這是我們自己的自裁權像我們目前這樣講備專為什麼要用我們配合的一台兩車機那兩車機就是我們自裁權對 其實想想也是因為如果組裝時的走那我買了一台成績拆機其實也可以學走有些有些說法你不知道老實說你不可能量那麼細但是大約形狀總超出來了解所以目前就是像這種我用鞋立廠商然後想辦法用外包的方法去解決這個產能的問題對這個解決的速度應該就會快滿多的對 就比起擴廠來說擴廠還有我們剛好剛好就是兩年前有開始建一個新廠剛好去年年底開始啟用今年就開商用廠那產能也多了可以做了一兩百台出來了解這個你有預期它會維持多久嗎就是要持續就是提高產能的這件事情很多人會就是說到底明年怎樣後年怎樣我說我又不是預測的大概今年階段之內的問題明年也是有人在訂所以今年明年兩年看起來是還可以那後年其實沒有人能保證看不到就以你目前所以目前的一些提升產能的規劃大概就做完了我們就是規劃完了接下來就是去做而已就還是你會有因為我想起說這個我產能不夠了我要加產能這個一個週期一次考量大概是多長的時間會考量一次預訂單還是預訂單來看預訂單如果真的是就是當然你訂單有那種不是說人家要給你訂的時候你才增加那你不行你那個到底有多緊然後是不是後面會再持續增加你就開始下去做這些事情不能等人家說給你報了但是等不及那一定是轉給別人了所以這個是在你全滿之後你需要再加再去加了解所以就一樣就是以我新增訂單的量來評估說我需不需要是不是要考慮加產能這件事情對了解那最近其實我們也會看到很多的這個班長開始要往東南亞走因為他們可能就台灣的場地已經不夠了這樣子我不太確定原因可是他們開始大概有很還有那個地緣政治的風險主要是地緣政治他們主要就再往東南亞走這邊你們會有怎麼樣的因應嗎其實他已經走了一段時間了不是剛開始他已經走一兩年而且場都蓋好蓋生產了那這對設備場來講是好事因為他到那邊也不是用舊機器就會直接買新的所以那邊其實也是一個對設備場來講是一個契機但對他們講也許是個噩夢對他們來講應該是因為去的人生地不守地又不是走講話與地方老實說文化也不一樣都不一樣我目前聽到的去東南亞走可是他成本又高可是一定要去但是他訂單他就告訴你訂單會先到那邊對他都要去就是講說聖旨在那邊你就不能到那邊走你就只能去了要不然怎麼辦可是對你們來說你們會需要在那邊也要有人嗎還是其實不太需要我們其實在泰國在越南都起步滿早的我們在十幾年前就已經佈典了因為最近需求不大所以把點再擴大然後目前還可以滿足客戶的需求因為台灣一個好處就是台灣之前有外來的勞工我們也會有請幾個然後他們好的部分就想回去就回去請到請那邊剛才在那邊就做大量的東西對這樣子帶起來這個會比大陸的還要快因為大陸只能從來而且你又不信任它那我們對他們是完全信任因為大家降渡太久了就以前先合作過了像東南亞那些你們也是在做廠嗎還是就是也是要做製造我們現在做設備室安裝然後後續的一些尾堡那另外在半導體的部分你會拜訪東南亞跑嗎還有半導體往日本跑嗎看看有沒有需要當然我們有實驗的有賣一台兩台過去這個量都比較少台灣過去就可以了還不需要佈典了解喔蠻有趣的SKAR有什麼問題嗎想要跟金友聊一下就是說過去PZP其實有好幾個循環你們為什麼怎麼看這一次的循環因為其實它過去的它篩口其實蠻長的通常是四五年對啊我倒這樣看起來加上這四五年一次四五年一次然後這次是很特別很特別的就是在2023年的時候是我們的朋友或者是代理商他都講說從來都沒有看過一個月都沒有人來問定用幾台的喔 真的那時候很慘超慘的那時候是消庫存就是疫情22年那一次這個東西漲太多了對 疫情末大家在被庫存被太多了那庫存都沒有消掉要你機器蓋什麼所以那時候就覺得從來沒看過那麼慘比2008還慘2008還有零星的那種一個兩個而且對大家會想2008他們是電器下降所以他們平常平常沒那麼大還好沒那麼大而且那時候笑那幾個人就吃飽了幾台機器就吃飽了那現在已經大了所以這種情況就變得非常的大家覺得就有點悲觀有點悲觀那過幾年之後突然就整個上去的那種其實不只我們是所有幾乎設備廠 板廠只要做到AY這個快的其實都知道都是漲得非常厲害主要是訂單需求這邊還有就是不只訂單需求它的單價那個需求單價也變高了是那大家也是說到底哪時候可以會有這種有時候沒有預警就下去了對啊那更能認為這跟效果存在是完全不一樣的現在你要看到的使用者是誰你一般那個像手機它有循環都不可以有循環有的那種在家經濟那是屬於N user的就是你一般的consumer的消費型的可是現在買的是誰是大雲上甚至未來的像那種大陸的政府或者是各個地方的政府做自主的就是AY主權AI的CAAI的這些它是計畫性的它如果不照這個走它就是關門對所以它不會立即下去那除非就是說哪一家爆雷了突然不見了除了現在這樣子風向不對對 除了現在這樣子就是撐不下去了除了這樣不然它會它必須要持續投下去是它沒辦法活合理因為剛剛其實前面提到也是那個嘛像那個Galton這個東西對 越來越多利用嘛對 隨便一般上這個它的買的這個會是比較偏這種Seph上的這種採購模式就是每一年就是固定我原本可以講說其實它比較不是跟消費性商品的循環做它計畫性的對 它比較對 是相比之下的話可能就有點像水泥吧是所以PCC的這種循環吧或者說這一次的循環或者說我們剛剛來講應該說不只是PCC應該說全部都是就是跟AI相關的這個它會轉成這種比較偏計畫型的這種採購方式除非它飽和了對 除非它飽和但是目前看起來它的採用率還還行還普通不夠高不夠高我這樣說好了你在嫌AI不夠好用它就持續會發展對還沒有到非常好用已經算不錯了你以為嫌它不好用它就會一直發展對我是覺得它真的已經快要可以取代我90%的工作我覺得有點可怕我是覺得也它沒辦法從早到晚去服侍你就不行為什麼沒錯因為未來未來很簡單就要一個機器的可能我們沒有做機器的也是一個大的項目對為什麼機器人會這樣因為未來就是我跟朋友講說到未來在醫院裡面可能不是故事看著你是機器人在照顧你再一次避難的趨勢算是避難的趨勢這一塊都還沒有這一塊很難算是去遠的話因為黃倫勳說機器人會是未來什麼第二大的產業還是第二個破譯的產業是不是王岐浩的用詞是什麼他說Fiscal AI他講機器人等一下講機器人那如果是這一塊機器人裡面應該也會需要很多板都會跟你們有關嗎還是他原來不知道對目前我們跟我們有關的是做板子這一塊所以它一樣是像在AI板那邊對但是有一點我們可能可以沾到邊就是控制這一塊但是這一塊是抗無Viva去切進去AI的控制嗎不是機器人的那個那個的本身控制器為什麼你才知道有一家做控制器的它紅是紅在它要做機器人對吧現在有一個也是1000多的是台灣的上市的他來過對台灣做控制器的那一家CNC的既然你可以他可以我也可以那因為都是控制器那是說我也也可以只是說我要不要切入因為這邊其實在太多事情那邊是未來是不是要規劃那你不要過去踩下去腳伸不出來所以還是要好好的評估對是因為都是控制器講說都是控制器但那邊都好不一樣你過去一定要一定會有學習成本而且玩家也不太一樣對啊商業模式也不一樣對所以就是你不會這樣做人形做其他的也可以你可以做狗狗是最多人跟我講的狗嗎我要只要大陸一碰那個就是捲對啊沒有狗有好處因為有一些是輪子過不去的對不是你也過去壞你不要以為你裝個履帶可以我們好像之前到Podcast聊過有一些好像就是都污戰在那個時候其實就有就有大量的狗的機器人在做一些人狗在某一些地形是很好的或者在什麼什麼探查什麼未爆彈什麼的類似這種它爆掉它對就損失一台機器對就還好那所以監督你現在在PCB還有看什麼新的技術嗎你們覺得現在未來因為現在其實蠻多人在講的比如說什麼GoWarp這些的你們有還有看到什麼新的這些變化嗎我們是科物標本是嗎好有有新東西我們會會盡量去做像最近剛剛講的是科物有一個需求是以前我們陳寗機大概是接板子大概是10mm後倒點那現在因為AI它要模擬板疊合在一起所以它的厚度高達30mm是那一般的機器已經陳寗機沒辦法做了所以他拿著Project給我們也自己在想要怎麼去突破是那這個就是難點難點就是我其實找那個能切的東西在推動控制器在設計把它慢慢弄出來這樣子是所以簡單來說就是跟著客戶的需求走大客戶的客戶有比較大的需求或者說這個客戶是大客戶的話你們就是配合他們開發但倍專這個應該理論上就是用在高速的這個訊號的傳輸所以是未來的只要相關的有高速訊號的理論上都有機會用到就對了對就是倍專的高速的是越來越多是不是它是它的成長是越來越快了解那很多東西就轉高速高速是不是幾乎等同於AI就像有除了AI也會要高速的原因地方嗎A字也有高速的可是A字也是AI你也在講現在要切什麼什麼都可以接它的定義應該是你需要訊號很快或者是傳輸要很快現在基本上就是主要會用到就能夠有AI的關係有另外一個是我們剛剛聊到CCD的成形機就是光模塊因為其實光模塊量變得很大而是說之前就不小了現在是大的可怕我們不能說不是很不小現在是用跳的你們覺得它是會它這個模式就是說看起來就是越來越小越來越快所以要怎麼說就是你們的未來會對這個這個東西你們會怎麼看你們就是覺得說成形機也是會像是剛剛做高速訊號那種東西一樣它會有更多的變化嗎為什麼會有變化因為我們會想一些新的點子去吸引客戶是你們想我會想很開譬如說我現在我們就有申請一個專輯就是我要做就是成形跟檢測在一起因為他們的通點就是我做完之後做得好不好沒有報告要拿到電台機去檢那我想辦法把它併在一起讓客戶去這個辦導體也蠻多的對不對我這我不清楚你辦導體也都做完一個字你都拍完對我們做塗膠類也是他們要求我們是塗完之後還要去檢測那個厚度還要再同一台檢測對就你們都多帶一台UI或者是那個AOM它要整個檢查好之後才能下就是外溢到其他的行業了對那我就一說我們這個東西做出來也就是一個亮點我的吸引客戶就是我們比別人多這些東西了解其實高階的這部分其實真的我跟你們一樣有關係不管是背專規格或者這種規格我們都做到前面甚至我們去展覽的時候就把新規格推出去之後然後別家就會但是德國的就過來看看幾個半年之後為什麼他們也有了中國也有來看吧我們剛才講控制器的那個機器的這個可以講不會說自己寫的就許某跟大廚這個就沒有辦法這三位競爭對你申請不了專業就會變成就職家要是我回去看我也看大家都保護超好不好看那麼多出來而已好多的東西互相參考對致敬對虧待的對好我們其實在邀請每個來賓其實後面都會有幾個定番問題像整種是喜歡看書的人嗎一般用時間才看最近有沒有比較推薦身邊的人怎麼樣是或者你最近讀到一本你覺得很不錯的書最近就比較忙我應該就這樣講就是陸陸續續就真的對我比較有影響的應該是很久沒被老書裡面寫的其實我有因為一部分是有去實踐他這一本叫做A到A家GurlitzGurlitz對那個就是對實踐是有用的其他都是練功法譬如說第五第五項修練他就練功法了那個只是心理而已那個原子習慣那個是自己習慣堅持兩三天就沒有了那你什麼用沒有成功使用原子習慣我也是有看沒有用你是從A到A家嗎當然有在實踐上就是這本書我等一下後行的時間是怎麼時間因為他其實很沒有他很概念他很概念他也不是關於他有講很多歷史譬如說你要對的事情你就要想辦法去做是對嘛那他有些他不要不敢做那因為我們這種就是有時候不好意思是得罪別的那種喔然後想要這本書不對要這樣做因為理解這個些東西不太適合他堅持做對的事我還是把它請到適合的地方嗯理解OK有些不得不的選擇啦對理解好那因為我們的聽眾都是對投資啊或者對產業研究有興趣的人嘛那如果今天他們想要更研究大量科技或者是研究整個PCB設備產業監眾有沒有什麼建議的他們可以關注的指標來可以知道說這個產業啊或者是大量科技接下來的發展會怎麼樣嗯指標我通常都是看他營業他的科技我是看板廠的業餌對啊冠軍沒有其實大量是很好指標但是你他的指標在哪邊就是之前我就跟我們的同事講哪一家的機器賣買多一點就快點買他股票哈哈哈哈這個勝率有算過的是八成好太好了我想去問板廠這不都是資本質素的概念嗎對因為我們是最先知道的嘛階段階很猛哦我們是最先知道的嘛你們看你們的你們的客戶的我們的客戶的訂單這是最準的你這樣我拍不能說板子板有些是虛的你這樣拍你要法律會一直問你說最近有誰買哈哈哈哈客戶名指不能出現在馬上哈哈哈哈然後那你當胃嗎哈哈哈哈所以我就還是看一下說像你剛剛提到的可能就看一下大量他們的營收是怎麼樣所以這大概就可以推估說那你們的客戶們他們接下來在產能這邊的擴張該是怎麼樣是是是可是目前的瓶頸就是你們的產能哈哈哈哈沒有那有些循溫度也有關係是是循溫度很熱的話對不對因為一直下去如果是說停了啊突然停了之後就覺得他就但是他會訂了單紙他會收手如果可能是center們的問題了嗯嗯嗯目前應該是完全看不到這個狀況的剛剛講說不到40個沒有可是2023確實發生過就是訂了訂單之後就肯掉了哎後面就你要急車嗯就含著眼淚就推給他是是拿一點現金回來啦對對對對對而且我們在改機型你知道舊的我我已經把它推往前推了嗯那你再不出去就變成賣不出去對就變成呆帳呆料嗯了解了解非常感謝監獎金菜的分享就是真的是學到了很多啊對對對因為因為都是本來不知道沒有學到超多東西的我覺得可以理解是那個啦就看起來就其實你們現在很多苦工花了很多時間沒錯在搞這個就同樣就是賣一個還是喝個廢火該你們搞的是蠻久的嗯很多的心力啦對啊尤其是大家不知道你們怎麼會寫軟體啦哈哈哈哈這個控制器的能力我再好奇問一個問題那你們知道你們的設備在客戶那邊他們體力的擇舊年限是多長嗎不一定有些體五年有些體十年不會體太久啦可能你們被用二十年了那體五年不是很怪嗎他加速比較有良心的所以他不行加速擇舊哎對這個是比較偏向台資的加速擇舊我覺得買那麼多快你擇掉快點賺錢嗯那以其他的好不要說哈哈哈哈他可能擇舊的很長你剛開始買進去以為他賺錢對但是他擇舊很長懂了嗎甚至說時間拉長就有差了對對對對但你們的確你們的設備的確是可以用這麼長的時間為什麼我要提這麼短他最後一個直到最後他還剩一層對對怎麼會這樣這樣這樣那他主要是擇完舊之後他後面就是賺的嗯因為老實說以目前我們被專機進去以代工的形式來賺錢的話他一年就回來了嗯12個月的環本期間趕快買啊一年啊就12個月對12個月的太好了一般都算18個月以上因為他代工的金額是比較高因為是要技術的但是賠也是賠一堆嗯沒料做話一片就不知道幾台車開走了哈哈哈哈對但這個就是這個啦你出門好也期待大量科技在尖種的在領執下也即可以真正的日上我們今天這集就先到這邊喜歡的聽眾記得按下訂閱分享給前夢還有給我們五星好評感謝大家收聽我們下次再見拜拜拜拜拜拜",
  "summary": null
}